py16_9199/__init__.py
py16_9199/a10a.py
py16_9199/a1a.py
py16_9199/a1b.py
py16_9199/a2a.py
py16_9199/a3a.py
py16_9199/a4a.py
py16_9199/a5a.py
py16_9199/a6a.py
py16_9199/a7a.py
py16_9199/a8a.py
py16_9199/a9a.py
py16_9199-0.1.0.dist-info/METADATA
py16_9199-0.1.0.dist-info/WHEEL
py16_9199-0.1.0.dist-info/top_level.txt
py16_9199-0.1.0.dist-info/RECORD
